entrypoint/__init__.py
entrypoint/debug.py
entrypoint/main.py
docker_entrypoint-0.1.6.dist-info/LICENSE.txt
docker_entrypoint-0.1.6.dist-info/METADATA
docker_entrypoint-0.1.6.dist-info/WHEEL
docker_entrypoint-0.1.6.dist-info/entry_points.txt
docker_entrypoint-0.1.6.dist-info/top_level.txt
docker_entrypoint-0.1.6.dist-info/RECORD
