Metadata-Version: 2.1
Name: docker-entrypoint
Version: 0.1.6
Summary: Basic utility to proxy a container's normal entrypoint
Home-page: https://github.com/PlaidCloud/docker-entrypoint
Author: Garrett Bates, Dave Parsons
Author-email: garrett.bates@tartansolutions.com, dave.parsons@tartansolutions.com
License: MIT
Keywords: container kubernetes debug development
Platform: UNKNOWN
Classifier: Programming Language :: Python :: 3.7
Classifier: License :: OSI Approved :: MIT License
Classifier: Operating System :: Unix
Requires-Python: >=3.7
Requires-Dist: python-dotenv
Requires-Dist: ptvsd
Requires-Dist: pydevd-pycharm
